{
  "walk_forward_folds": 14,
  "folds": [
    {
      "fold": 1,
      "val_acc": -0.003325777832786218,
      "val_mae": 0.003325777832786218,
      "directional_acc": 0.5292326431181485
    },
    {
      "fold": 2,
      "val_acc": -0.0025004918815230044,
      "val_mae": 0.0025004918815230044,
      "directional_acc": 0.5724725943970768
    },
    {
      "fold": 3,
      "val_acc": -0.005067480324192401,
      "val_mae": 0.005067480324192401,
      "directional_acc": 0.46345919610231423
    },
    {
      "fold": 4,
      "val_acc": -0.005636758144931294,
      "val_mae": 0.005636758144931294,
      "directional_acc": 0.52557856272838
    },
    {
      "fold": 5,
      "val_acc": -0.005405733293777697,
      "val_mae": 0.005405733293777697,
      "directional_acc": 0.5645554202192449
    },
    {
      "fold": 6,
      "val_acc": -0.005118354832828408,
      "val_mae": 0.005118354832828408,
      "directional_acc": 0.510353227771011
    },
    {
      "fold": 7,
      "val_acc": -0.004464164646240303,
      "val_mae": 0.004464164646240303,
      "directional_acc": 0.44945188794153473
    },
    {
      "fold": 8,
      "val_acc": -0.003250166308701982,
      "val_mae": 0.003250166308701982,
      "directional_acc": 0.5304506699147381
    },
    {
      "fold": 9,
      "val_acc": -0.004483946938244637,
      "val_mae": 0.004483946938244637,
      "directional_acc": 0.5468940316686967
    },
    {
      "fold": 10,
      "val_acc": -0.006182924060470875,
      "val_mae": 0.006182924060470875,
      "directional_acc": 0.523142509135201
    },
    {
      "fold": 11,
      "val_acc": -0.006574362320156176,
      "val_mae": 0.006574362320156176,
      "directional_acc": 0.5529841656516443
    },
    {
      "fold": 12,
      "val_acc": -0.00568178954480917,
      "val_mae": 0.00568178954480917,
      "directional_acc": 0.49634591961023145
    },
    {
      "fold": 13,
      "val_acc": -0.004365448189965119,
      "val_mae": 0.004365448189965119,
      "directional_acc": 0.6132764920828259
    },
    {
      "fold": 14,
      "val_acc": -0.005103888262367277,
      "val_mae": 0.005103888262367277,
      "directional_acc": 0.548721071863581
    }
  ],
  "val_acc_aggregate": -0.004797234755785326,
  "feature_cols": [
    "open",
    "high",
    "low",
    "close",
    "volume",
    "ATR_4",
    "ATR_6",
    "EMA_6",
    "RSI_6",
    "VWAP_6",
    "ROC_6",
    "KC_upper_6",
    "KC_middle_6",
    "Donchian_upper_6",
    "Donchian_lower_6",
    "MACD_6",
    "MACD_signal_6",
    "BB_upper_6",
    "BB_middle_6",
    "BB_lower_6",
    "EWO_6",
    "ATR_8",
    "EMA_8",
    "RSI_8",
    "VWAP_8",
    "ROC_8",
    "KC_upper_8",
    "KC_middle_8",
    "Donchian_upper_8",
    "Donchian_lower_8",
    "MACD_8",
    "MACD_signal_8",
    "BB_upper_8",
    "BB_middle_8",
    "BB_lower_8",
    "EWO_8",
    "ATR_10",
    "EMA_10",
    "RSI_10",
    "VWAP_10",
    "ROC_10",
    "KC_upper_10",
    "KC_middle_10",
    "Donchian_upper_10",
    "Donchian_lower_10",
    "MACD_10",
    "MACD_signal_10",
    "BB_upper_10",
    "BB_middle_10",
    "BB_lower_10",
    "EWO_10",
    "ATR_12",
    "EMA_12",
    "RSI_12",
    "VWAP_12",
    "ROC_12",
    "KC_upper_12",
    "KC_middle_12",
    "Donchian_upper_12",
    "Donchian_lower_12",
    "MACD_12",
    "MACD_signal_12",
    "BB_upper_12",
    "BB_middle_12",
    "BB_lower_12",
    "EWO_12",
    "ATR_14",
    "EMA_14",
    "RSI_14",
    "VWAP_14",
    "ROC_14",
    "KC_upper_14",
    "KC_middle_14",
    "Donchian_upper_14",
    "Donchian_lower_14",
    "MACD_14",
    "MACD_signal_14",
    "BB_upper_14",
    "BB_middle_14",
    "BB_lower_14",
    "EWO_14",
    "ATR_16",
    "EMA_16",
    "RSI_16",
    "VWAP_16",
    "ROC_16",
    "KC_upper_16",
    "KC_middle_16",
    "Donchian_upper_16",
    "Donchian_lower_16",
    "MACD_16",
    "MACD_signal_16",
    "BB_upper_16",
    "BB_middle_16",
    "BB_lower_16",
    "EWO_16",
    "ATR_18",
    "EMA_18",
    "RSI_18",
    "VWAP_18",
    "ROC_18",
    "KC_upper_18",
    "KC_middle_18",
    "Donchian_upper_18",
    "Donchian_lower_18",
    "MACD_18",
    "MACD_signal_18",
    "BB_upper_18",
    "BB_middle_18",
    "BB_lower_18",
    "EWO_18",
    "ATR_22",
    "EMA_22",
    "RSI_22",
    "VWAP_22",
    "ROC_22",
    "KC_upper_22",
    "KC_middle_22",
    "Donchian_upper_22",
    "Donchian_lower_22",
    "MACD_22",
    "MACD_signal_22",
    "BB_upper_22",
    "BB_middle_22",
    "BB_lower_22",
    "EWO_22",
    "ATR_26",
    "EMA_26",
    "RSI_26",
    "VWAP_26",
    "ROC_26",
    "KC_upper_26",
    "KC_middle_26",
    "Donchian_upper_26",
    "Donchian_lower_26",
    "MACD_26",
    "MACD_signal_26",
    "BB_upper_26",
    "BB_middle_26",
    "BB_lower_26",
    "EWO_26",
    "ATR_33",
    "EMA_33",
    "RSI_33",
    "VWAP_33",
    "ROC_33",
    "KC_upper_33",
    "KC_middle_33",
    "Donchian_upper_33",
    "Donchian_lower_33",
    "MACD_33",
    "MACD_signal_33",
    "BB_upper_33",
    "BB_middle_33",
    "BB_lower_33",
    "EWO_33",
    "ATR_44",
    "EMA_44",
    "RSI_44",
    "VWAP_44",
    "ROC_44",
    "KC_upper_44",
    "KC_middle_44",
    "Donchian_upper_44",
    "Donchian_lower_44",
    "MACD_44",
    "MACD_signal_44",
    "BB_upper_44",
    "BB_middle_44",
    "BB_lower_44",
    "EWO_44",
    "ATR_55",
    "EMA_55",
    "RSI_55",
    "VWAP_55",
    "ROC_55",
    "KC_upper_55",
    "KC_middle_55",
    "Donchian_upper_55",
    "Donchian_lower_55",
    "MACD_55",
    "MACD_signal_55",
    "BB_upper_55",
    "BB_middle_55",
    "BB_lower_55",
    "EWO_55",
    "return",
    "Range",
    "Volatility",
    "OBV",
    "ADL",
    "Stoch_Oscillator",
    "PSAR",
    "adx"
  ],
  "num_params": 915585,
  "config": {
    "data_path": "/opt/ml/input/data/train",
    "output_dir": "/opt/ml/model",
    "meta_path": "/opt/ml/model/model_meta.json",
    "window_size": 90,
    "hidden_size": 128,
    "num_layers": 2,
    "dropout": 0.1,
    "bidirectional": false,
    "epochs": 40,
    "batch_size": 32,
    "learning_rate": 0.0001,
    "weight_decay": 0.0005,
    "val_frac": 0.15,
    "accumulate": 2,
    "seed": 434,
    "price_col": "close",
    "tp_pct": 0.01,
    "sl_pct": 0.005,
    "time_limit": 30,
    "amp": true,
    "workers": 0,
    "chunksize": 500000,
    "task": "regression",
    "horizon": 60,
    "model_type": "performer_bilstm",
    "max_folds": null,
    "use_class_weights": true,
    "use_focal_loss": true,
    "focal_gamma": 2.0,
    "calibrate_temp": true
  }
}